typedmodels/__init__.py
typedmodels/admin.py
typedmodels/models.py
typedmodels/py.typed
typedmodels/tests.py
django_typed_models-0.15.1.dist-info/METADATA
django_typed_models-0.15.1.dist-info/WHEEL
django_typed_models-0.15.1.dist-info/licenses/LICENSE.txt
django_typed_models-0.15.1.dist-info/RECORD
