Metadata-Version: 2.4
Name: django-typed-models
Version: 0.15.1
Summary: Sane single table model inheritance for Django
Project-URL: Homepage, https://github.com/craigds/django-typed-models
Author-email: Craig de Stigter <craig@destigter.nz>
License-Expression: BSD-3-Clause
License-File: LICENSE.txt
Classifier: Environment :: Web Environment
Classifier: Framework :: Django
Classifier: Framework :: Django :: 4.2
Classifier: Framework :: Django :: 5.1
Classifier: Framework :: Django :: 5.2
Classifier: Framework :: Django :: 6.0
Classifier: Intended Audience :: Developers
Classifier: License :: OSI Approved :: BSD License
Classifier: Operating System :: OS Independent
Classifier: Programming Language :: Python
Classifier: Programming Language :: Python :: 3
Classifier: Programming Language :: Python :: 3 :: Only
Classifier: Programming Language :: Python :: 3.10
Classifier: Programming Language :: Python :: 3.11
Classifier: Programming Language :: Python :: 3.12
Classifier: Programming Language :: Python :: 3.13
Classifier: Topic :: Utilities
Requires-Python: >=3.10
Requires-Dist: django-stubs-ext
Requires-Dist: typing-extensions
